Reqtxt/__init__.py
Reqtxt/reqtxt.py
Reqtxt-1.0.dist-info/METADATA
Reqtxt-1.0.dist-info/RECORD
Reqtxt-1.0.dist-info/WHEEL
Reqtxt-1.0.dist-info/top_level.txt
